odoo/addons/mitxelena/__init__.py
odoo/addons/mitxelena/__manifest__.py
odoo/addons/mitxelena/models/__init__.py
odoo/addons/mitxelena/models/product_template.py
odoo/addons/mitxelena/models/res_partner.py
odoo/addons/mitxelena/models/sale_order_line.py
odoo/addons/mitxelena/views/product_template.xml
odoo/addons/mitxelena/views/res_partner.xml
odoo/addons/mitxelena/views/sale_order_line.xml
odoo12_addon_mitxelena-12.0.0.0.1.dist-info/METADATA
odoo12_addon_mitxelena-12.0.0.0.1.dist-info/WHEEL
odoo12_addon_mitxelena-12.0.0.0.1.dist-info/top_level.txt
odoo12_addon_mitxelena-12.0.0.0.1.dist-info/RECORD
