Metadata-Version: 2.1
Name: odoo12-addon-mitxelena
Version: 12.0.0.0.1
Summary: Manufacturing customisation for Talleres mitxelena
Home-page: https://gitlab.com/coopdevs
Author: Coopdevs Treball SCCL
License: UNKNOWN
Platform: UNKNOWN
Classifier: Programming Language :: Python
Classifier: Framework :: Odoo
Classifier: Framework :: Odoo :: 12.0
Requires-Python: >=3.5
Requires-Dist: odoo12-addon-base-revision
Requires-Dist: odoo12-addon-product-supplierinfo-for-customer
Requires-Dist: odoo (<12.1dev,>=12.0a)
